thehouse/__init__.py
thehouse/__main__.py
thehouse/characters/__init__.py
thehouse/characters/character.py
thehouse/characters/monster.py
thehouse/characters/player.py
thehouse/helpers/__init__.py
thehouse/helpers/constants.py
thehouse/helpers/print_pause.py
thehouse/helpers/random_death.py
thehouse/helpers/validate_input.py
thehouse/play.py
thehouse/rooms/__init__.py
thehouse/rooms/bedroom.py
thehouse/rooms/diningroom.py
thehouse/rooms/hall.py
thehouse/rooms/hallway.py
thehouse/rooms/kitchen.py
thehouse/rooms/livingroom.py
thehouse/rooms/room.py
thehouse/rooms/studio.py
thehouse/thehouse.py
thehouse-3.0.1.dist-info/METADATA
thehouse-3.0.1.dist-info/WHEEL
thehouse-3.0.1.dist-info/entry_points.txt
thehouse-3.0.1.dist-info/licenses/LICENSE
thehouse-3.0.1.dist-info/RECORD
