Metadata-Version: 2.4
Name: thehouse
Version: 3.0.1
Summary: A text-based horror game
License: MIT
License-File: LICENSE
Author: Davide Di Criscito
Author-email: dcdavidev@gmail.com
Requires-Python: >=3.12
Classifier: Topic :: Games/Entertainment
